torchmix/__init__.py
torchmix/components/__init__.py
torchmix/components/attention/__init__.py
torchmix/components/attention/base.py
torchmix/components/attention/plugin.py
torchmix/components/attention/vit.py
torchmix/components/container/__init__.py
torchmix/components/container/arithmetic.py
torchmix/components/container/attach.py
torchmix/components/container/drop.py
torchmix/components/container/norm.py
torchmix/components/container/repeat.py
torchmix/components/embedding.py
torchmix/components/feedforward/__init__.py
torchmix/components/feedforward/base.py
torchmix/components/feedforward/plugin.py
torchmix/components/pool.py
torchmix/core/__init__.py
torchmix/core/_builds.py
torchmix/core/_context.py
torchmix/core/component.py
torchmix/nn/__codegen.py
torchmix/nn/__init__.py
torchmix/py.typed
torchmix/third_party/__init__.py
torchmix/third_party/einops.py
torchmix-0.1.0rc8.dist-info/LICENSE
torchmix-0.1.0rc8.dist-info/WHEEL
torchmix-0.1.0rc8.dist-info/METADATA
torchmix-0.1.0rc8.dist-info/RECORD
