Metadata-Version: 2.1
Name: torchmix
Version: 0.1.0rc8
Summary: Flexible components for transformers 🧩
Author: junhsss
Author-email: junhsssr@gmail.com
Requires-Python: >=3.8
Classifier: Programming Language :: Python :: 3
Classifier: Programming Language :: Python :: 3.8
Classifier: Programming Language :: Python :: 3.9
Classifier: Programming Language :: Python :: 3.10
Classifier: Programming Language :: Python :: 3.11
Requires-Dist: einops (>=0.6.0)
Requires-Dist: hydra-core (>=1.0.0)
Requires-Dist: hydra-zen (>=0.8.0)
Requires-Dist: jaxtyping (>=0.2.0)
